{
  "collectionName": "components_common_two_column_blocks",
  "info": {
    "displayName": "ComponentCommonTwoColumnBlock",
    "icon": "address-card",
    "description": ""
  },
  "options": {},
  "attributes": {
    "Title": {
      "type": "string"
    },
    "Description": {
      "type": "text"
    },
    "Click": {
      "type": "string"
    },
    "ButtonUrl": {
      "type": "string"
    },
    "ImagePosition": {
      "type": "enumeration",
      "enum": [
        "Left",
        "Right"
      ]
    },
    "Image": {
      "type": "media",
      "multiple": true,
      "required": false,
      "allowedTypes": [
        "images",
        "files",
        "videos",
        "audios"
      ]
    }
  }
}
